testpage3/__init__.py
testpage3/launch.py
SybNoChill-0.0.3.dist-info/LICENSE
SybNoChill-0.0.3.dist-info/METADATA
SybNoChill-0.0.3.dist-info/WHEEL
SybNoChill-0.0.3.dist-info/top_level.txt
SybNoChill-0.0.3.dist-info/RECORD
