Metadata-Version: 2.1
Name: SybNoChill
Version: 0.0.3
Summary: testpage3 cython
Home-page: https://github.com/pypa/sampleproject
Author: Sybren
Author-email: sybren.vuylsteke@hotmail.com
License: UNKNOWN
Project-URL: Bug Tracker, https://github.com/pypa/sampleproject/issues
Platform: UNKNOWN
Classifier: Programming Language :: Python :: 3
Classifier: License :: OSI Approved :: MIT License
Classifier: Operating System :: OS Independent
Requires-Python: >=3.6
License-File: LICENSE
